k8svag
